text2digits/__init__.py
text2digits/t2d.py
text2digits/text2digits.py
text2digits_careless25-0.0.2.dist-info/LICENSE
text2digits_careless25-0.0.2.dist-info/METADATA
text2digits_careless25-0.0.2.dist-info/WHEEL
text2digits_careless25-0.0.2.dist-info/top_level.txt
text2digits_careless25-0.0.2.dist-info/RECORD
