Metadata-Version: 2.1
Name: text2digits-careless25
Version: 0.0.2
Summary: A small library to convert text numbers to digits in a string
Home-page: https://github.com/careless25/text2digits
Author: Shail Choksi
Author-email: choksishail@gmail.com
License: UNKNOWN
Platform: UNKNOWN
Classifier: Programming Language :: Python :: 3
Classifier: License :: OSI Approved :: MIT License
Classifier: Operating System :: OS Independent
